README.md
setup.py
pykmtronic/__init__.py
pykmtronic/auth.py
pykmtronic/consts.py
pykmtronic/hub.py
pykmtronic/relay.py
pykmtronic.egg-info/PKG-INFO
pykmtronic.egg-info/SOURCES.txt
pykmtronic.egg-info/dependency_links.txt
pykmtronic.egg-info/requires.txt
pykmtronic.egg-info/top_level.txt
pykmtronic.egg-info/zip-safe