Metadata-Version: 2.1
Name: pykmtronic
Version: 0.2.0
Summary: Python library to interface with KM Tronic Web Relays
Home-page: https://github.com/dgomes/pykmtronic
Author: Diogo Gomes
Author-email: diogogomes@gmail.com
License: MIT License
Platform: any
Classifier: License :: OSI Approved :: MIT License
Classifier: Intended Audience :: Developers
Classifier: Operating System :: OS Independent
Classifier: Programming Language :: Python
Classifier: Programming Language :: Python :: 3
Classifier: Topic :: Software Development :: Libraries :: Python Modules
